{
  "placeholderImages": [
    {
      "id": "login-image",
      "description": "A compassionate doctor assisting a patient.",
      "imageUrl": "https://images.unsplash.com/photo-1631217871099-88310a909a32?crop=entropy&cs=tinysrgb&fit=max&fm=jpg&ixid=M3w3NDE5ODJ8MHwxfHNlYXJjaHw0fHxkb2N0b3IlMjBwYXRpZW50fGVufDB8fHx8MTc2OTY2NzEzNnww&ixlib=rb-4.1.0&q=80&w=1080",
      "imageHint": "doctor patient"
    },
    {
      "id": "user-avatar-1",
      "description": "User avatar",
      "imageUrl": "https://images.unsplash.com/photo-1594950444552-d55891393c8c?q=80&w=800&auto=format&fit=crop",
      "imageHint": "indian man"
    },
    {
      "id": "doctor-avatar-1",
      "description": "Portrait of Dr. Priya Sharma",
      "imageUrl": "https://images.unsplash.com/photo-1638351892949-8b83965a3962?q=80&w=800&auto=format&fit=crop",
      "imageHint": "indian doctor"
    },
    {
      "id": "doctor-avatar-2",
      "description": "Portrait of Dr. Rohan Gupta",
      "imageUrl": "https://images.unsplash.com/photo-1532938912279-418a5b239763?q=80&w=800&auto=format&fit=crop",
      "imageHint": "indian doctor"
    },
    {
      "id": "doctor-avatar-3",
      "description": "Portrait of Dr. Anjali Patel",
      "imageUrl": "https://images.unsplash.com/photo-1630028216298-6a235de98274?q=80&w=800&auto=format&fit=crop",
      "imageHint": "indian doctor"
    },
    {
      "id": "doctor-avatar-4",
      "description": "Portrait of Dr. Vikram Singh",
      "imageUrl": "https://images.unsplash.com/photo-1599609028822-421019d03c8b?q=80&w=800&auto=format&fit=crop",
      "imageHint": "indian doctor"
    },
    {
      "id": "doctor-avatar-5",
      "description": "Portrait of Dr. Sunita Rao",
      "imageUrl": "https://images.unsplash.com/photo-1619864218317-e2474b71f76a?q=80&w=800&auto=format&fit=crop",
      "imageHint": "indian doctor"
    },
    {
      "id": "doctor-avatar-6",
      "description": "Portrait of Dr. Amit Kumar",
      "imageUrl": "https://images.unsplash.com/photo-1600885141021-0811370b3c66?q=80&w=800&auto=format&fit=crop",
      "imageHint": "indian doctor"
    }
  ]
}